odoo/addons/stock_deferred_assign/README.rst
odoo/addons/stock_deferred_assign/__init__.py
odoo/addons/stock_deferred_assign/__manifest__.py
odoo/addons/stock_deferred_assign/i18n/es.po
odoo/addons/stock_deferred_assign/i18n/stock_deferred_assign.pot
odoo/addons/stock_deferred_assign/migrations/13.0.1.0.0/pre-migration.py
odoo/addons/stock_deferred_assign/models/__init__.py
odoo/addons/stock_deferred_assign/models/sale.py
odoo/addons/stock_deferred_assign/models/stock_move.py
odoo/addons/stock_deferred_assign/models/stock_picking.py
odoo/addons/stock_deferred_assign/models/stock_picking_type.py
odoo/addons/stock_deferred_assign/models/stock_rule.py
odoo/addons/stock_deferred_assign/readme/CONFIGURATION.rst
odoo/addons/stock_deferred_assign/readme/CONTRIBUTORS.rst
odoo/addons/stock_deferred_assign/readme/DESCRIPTION.rst
odoo/addons/stock_deferred_assign/static/description/icon.png
odoo/addons/stock_deferred_assign/static/description/index.html
odoo/addons/stock_deferred_assign/tests/__init__.py
odoo/addons/stock_deferred_assign/tests/test_stock_deferred_assign.py
odoo/addons/stock_deferred_assign/views/picking_type.xml
odoo13_addon_stock_deferred_assign-13.0.1.0.1.dev6.dist-info/METADATA
odoo13_addon_stock_deferred_assign-13.0.1.0.1.dev6.dist-info/WHEEL
odoo13_addon_stock_deferred_assign-13.0.1.0.1.dev6.dist-info/top_level.txt
odoo13_addon_stock_deferred_assign-13.0.1.0.1.dev6.dist-info/RECORD
